
{
    "R0": {"lat": "47:22:50.81874", "lon": "2:11:35.93258", "height": 182.774},
    "R1": {"lat": "47:22:50.81713", "lon": "2:11:36.71091", "height": 182.758},
    "R2": {"lat": "47:22:50.81239", "lon": "2:11:37.45489", "height": 182.778},
    "R3": {"lat": "47:22:49.84997", "lon": "2:11:35.93436", "height": 182.772},
    "R4": {"lat": "47:22:49.85451", "lon": "2:11:36.69309", "height": 182.887},
    "R5": {"lat": "47:22:49.85289", "lon": "2:11:37.45860", "height": 182.932},
    "R6": {"lat": "47:22:48.87243", "lon": "2:11:35.92955", "height": 182.627},
    "R7": {"lat": "47:22:48.87186", "lon": "2:11:36.69549", "height": 182.718},
    "R8": {"lat": "47:22:48.88414", "lon": "2:11:37.45836", "height": 182.690},
    "L0": {"lat": "47:22:50.82526", "lon": "2:11:33.63644", "height": 182.883},
    "L1": {"lat": "47:22:50.82371", "lon": "2:11:34.39713", "height": 182.665},
    "L2": {"lat": "47:22:50.82189", "lon": "2:11:35.16440", "height": 182.781},
    "L3": {"lat": "47:22:49.83457", "lon": "2:11:33.63496", "height": 182.719},
    "L4": {"lat": "47:22:49.85154", "lon": "2:11:34.39895", "height": 182.674},
    "L5": {"lat": "47:22:49.85188", "lon": "2:11:35.15953", "height": 182.641},
    "L6": {"lat": "47:22:48.86362", "lon": "2:11:33.63348", "height": 182.630},
    "L7": {"lat": "47:22:48.87160", "lon": "2:11:34.39718", "height": 182.704},
    "L8": {"lat": "47:22:48.86703", "lon": "2:11:35.16086", "height": 182.576}
}